QIDLearningLib/__init__.py
QIDLearningLib/main.py
QIDLearningLib/metrics/__init__.py
QIDLearningLib/metrics/causality.py
QIDLearningLib/metrics/data_privacy.py
QIDLearningLib/metrics/data_utility.py
QIDLearningLib/metrics/performance.py
QIDLearningLib/metrics/qid_specific.py
QIDLearningLib/optimizer/__init__.py
QIDLearningLib/optimizer/graph.py
QIDLearningLib/optimizer/metric.py
QIDLearningLib/optimizer/util.py
QIDLearningLib/optimizer/evolutionary_algorithm/__init__.py
QIDLearningLib/optimizer/evolutionary_algorithm/evolutionary_algorithm.py
QIDLearningLib/optimizer/greedy_search/__init__.py
QIDLearningLib/optimizer/greedy_search/aggregated_results_greedy.csv
QIDLearningLib/optimizer/greedy_search/greedy_search.py
QIDLearningLib/optimizer/simulated_annealing/__init__.py
QIDLearningLib/optimizer/simulated_annealing/aggregated_results_sa.csv
QIDLearningLib/optimizer/simulated_annealing/simulated_annealing.py
QIDLearningLib/optimizer/tabu_search/__init__.py
QIDLearningLib/optimizer/tabu_search/tabu_search.py
QIDLearningLib/structure/__init__.py
QIDLearningLib/structure/grouped_metric.py
QIDLearningLib/test/__init__.py
QIDLearningLib/test/causality.py
QIDLearningLib/test/data_privacy.py
QIDLearningLib/test/data_utility.py
QIDLearningLib/test/performance.py
QIDLearningLib/test/qid_specific.py
QIDLearningLib/test/test_results_num_runs_3_df_size_10000.csv
QIDLearningLib/util/__init__.py
QIDLearningLib/util/data.py
QIDLearningLib/util/stats.py
QIDLearningLib/util/time.py
qidlearninglib-0.0.6.dist-info/METADATA
qidlearninglib-0.0.6.dist-info/WHEEL
qidlearninglib-0.0.6.dist-info/licenses/LICENSE
qidlearninglib-0.0.6.dist-info/RECORD
